{"cameraMode":{"drawMode":0,"name":"Shaded","section":"Shading Mode"},"sceneLighting":true,"audioPlay":false,"sceneViewState":{"m_AlwaysRefresh":false,"showFog":true,"showSkybox":true,"showFlares":true,"showImageEffects":true,"showParticleSystems":true,"showVisualEffectGraphs":true,"m_FxEnabled":true},"in2DMode":false,"pivot":{"x":1.6753730773925782,"y":-1.7881393432617188e-7,"z":0.24356162548065186},"rotation":{"x":0.03282745182514191,"y":0.6316013336181641,"z":-0.0266787800937891,"w":0.7742412090301514},"size":3.6864423751831056,"orthographic":false}